oss_client/__init__.py
oss_client/client.py
oss_client/fileobj.py
oss_client/utils.py
oss_client-0.1.4.dist-info/LICENSE
oss_client-0.1.4.dist-info/METADATA
oss_client-0.1.4.dist-info/WHEEL
oss_client-0.1.4.dist-info/top_level.txt
oss_client-0.1.4.dist-info/RECORD
