Metadata-Version: 2.1
Name: oss-client
Version: 0.1.4
Summary: OSS Client for AliyunOSS/TencentOSS/QiniuOSS
Home-page: https://github.com/olivetree123/oss-client
Author: olivetree
Author-email: olivetree123@163.com
License: MIT
Platform: UNKNOWN
License-File: LICENSE
Requires-Dist: requests (>=2.18.0)
Requires-Dist: oss2 (==2.15.0)
Requires-Dist: qiniu (==7.5.0)
Requires-Dist: cos-python-sdk-v5 (==1.9.10)
